Tiger_Assessment/IO_path.py
Tiger_Assessment/Tiger_Assessment.py
Tiger_Assessment/__init__.py
Tiger_Assessment/config.py
Tiger_Assessment/data_clean.py
Tiger_Assessment/data_process.py
Tiger_Assessment/merge.py
Tiger_Assessment/my_functions.py
Tiger_Assessment/summary_stats.py
Tiger_Assessment-0.0.17.dist-info/LICENSE.txt
Tiger_Assessment-0.0.17.dist-info/METADATA
Tiger_Assessment-0.0.17.dist-info/WHEEL
Tiger_Assessment-0.0.17.dist-info/top_level.txt
Tiger_Assessment-0.0.17.dist-info/RECORD
