Metadata-Version: 2.1
Name: Tiger-Assessment
Version: 0.0.17
Summary: Tiger_Assessment is a python package for developed as a part of interview process.
Home-page: https://github.com/sandeepkirangudla/tiger_assessment
Author: Sandeep Kiran Gudla
Author-email: gsandeepkiran@gmail.com
License: NA
Platform: UNKNOWN
Classifier: Development Status :: 4 - Beta
Classifier: License :: OSI Approved :: MIT License
Classifier: Programming Language :: Python
Classifier: Programming Language :: Python :: 3.5
Classifier: Programming Language :: Python :: 3.6
Classifier: Topic :: Software Development :: Libraries
Classifier: Topic :: Software Development :: Libraries :: Python Modules
Classifier: Intended Audience :: Developers
Requires-Python: >=3.5
Requires-Dist: pandas
Requires-Dist: numpy
